{
  "project_info": {
    "project_number": "918007435696",
    "firebase_url": "https://postboy-c4bc3.firebaseio.com",
    "project_id": "postboy-c4bc3",
    "storage_bucket": "postboy-c4bc3.appspot.com"
  },
  "client": [
    {
      "client_info": {
        "mobilesdk_app_id": "1:918007435696:android:747409adfc310e1dde4675",
        "android_client_info": {
          "package_name": "anicode.postboy"
        }
      },
      "oauth_client": [
        {
          "client_id": "918007435696-gmia199hlbmnkrvuklel8eql0s4ctl10.apps.googleusercontent.com",
          "client_type": 3
        }
      ],
      "api_key": [
        {
          "current_key": "AIzaSyArHSGVoslH9PpDBXPDCelIa-V5u6ckM3c"
        }
      ],
      "services": {
        "appinvite_service": {
          "other_platform_oauth_client": [
            {
              "client_id": "918007435696-gmia199hlbmnkrvuklel8eql0s4ctl10.apps.googleusercontent.com",
              "client_type": 3
            }
          ]
        }
      }
    }
  ],
  "configuration_version": "1"
}